LICENSE
gordo_core/__init__.py
gordo_core/_version.py
gordo_core/back_compatibles.py
gordo_core/base.py
gordo_core/data_providers/__init__.py
gordo_core/data_providers/base.py
gordo_core/data_providers/contrib/__init__.py
gordo_core/data_providers/contrib/csv_provider.py
gordo_core/data_providers/partition.py
gordo_core/data_providers/providers.py
gordo_core/data_providers/utils.py
gordo_core/dist.py
gordo_core/exceptions.py
gordo_core/file_systems/__init__.py
gordo_core/file_systems/base.py
gordo_core/filters/__init__.py
gordo_core/filters/periods.py
gordo_core/filters/rows.py
gordo_core/import_utils.py
gordo_core/metadata.py
gordo_core/sensor_tag.py
gordo_core/time_series.py
gordo_core/utils.py
gordo_core/validators.py
gordo_core-0.3.6.dist-info/LICENSE
gordo_core-0.3.6.dist-info/WHEEL
gordo_core-0.3.6.dist-info/METADATA
gordo_core-0.3.6.dist-info/RECORD
